COPYING.txt
MANIFEST.in
README
setup.py
gists/__init__.py
gists/actions.py
gists/formatters.py
gists/gists
gists/gists.py
gists/handlers.py
gists/literals.py
gists/model.py
gists/utils.py
gists/version.py
gists.egg-info/PKG-INFO
gists.egg-info/SOURCES.txt
gists.egg-info/dependency_links.txt
gists.egg-info/requires.txt
gists.egg-info/top_level.txt