Metadata-Version: 1.1
Name: gists
Version: 0.4.6
Summary: CLI interface to manage Github gists
Home-page: http://jdevesa.github.com/gists
Author: Jaume Devesa
Author-email: jaumedevesa@gmail.com
License: MIT
Platform: UNKNOWN
Classifier: Programming Language :: Python
Classifier: Programming Language :: Python :: 2.6
Classifier: Programming Language :: Python :: 2.7
Classifier: Development Status :: 5 - Production/Stable 
Classifier: Environment :: Console
Classifier: Intended Audience :: Developers
Classifier: License :: OSI Approved :: MIT License
Classifier: Natural Language :: English
Classifier: Operating System :: POSIX :: Linux
